sopel_modules.wolfram-0.4.1-py3.6-nspkg.pth
sopel_modules/wolfram/__init__.py
sopel_modules/wolfram/wolfram.py
sopel_modules.wolfram-0.4.1.dist-info/DESCRIPTION.rst
sopel_modules.wolfram-0.4.1.dist-info/METADATA
sopel_modules.wolfram-0.4.1.dist-info/RECORD
sopel_modules.wolfram-0.4.1.dist-info/WHEEL
sopel_modules.wolfram-0.4.1.dist-info/metadata.json
sopel_modules.wolfram-0.4.1.dist-info/namespace_packages.txt
sopel_modules.wolfram-0.4.1.dist-info/top_level.txt
tests/__init__.py
tests/test_wolfram.py
