Metadata-Version: 2.0
Name: sopel-modules.wolfram
Version: 0.4.1
Summary: Wolfram|Alpha module for Sopel IRC bot framework
Home-page: https://github.com/dgw/sopel-wolfram
Author: dgw
Author-email: sopel-wolfram@dgw.me
License: Eiffel Forum License, version 2
Platform: UNKNOWN
Requires-Dist: sopel (<7,>=6.0)
Requires-Dist: wolframalpha (<4.0,>=2.4)
